<?xml version="1.0" encoding="UTF-8"?>
<org.openmdx.base.Authority xmlns:xsi="http://www.w3.org/2001/XMLSchema-instance" name="org:openmdx:ui1" xsi:noNamespaceSchemaLocation="xri://+resource/org/openmdx/ui1/xmi1/ui1.xsd">
	<_object />
	<_content>
		<provider>
			<org.openmdx.base.Provider qualifiedName="CRX" _operation="null">
				<_object />
				<_content>
					<segment>
						<org.openmdx.ui1.Segment qualifiedName="Root" _operation="null">
							<_object />
							<_content>
								<elementDefinition>
									<!--these are extensions attributes, i.e. user-definable -->
									<!--Tab Definition -->
									<org.openmdx.ui1.ElementDefinition name="org:opencrx:kernel:account1:Account:Pane:Attr:Tab:91">
										<_object>
											<active>false</active>
											<toolTip>
												<_item>帳戶 / 使用者定義欄位</_item>
											</toolTip>
											<label>
												<_item>帳戶 / 使用者</_item>
											</label>
										</_object>
										<_content />
									</org.openmdx.ui1.ElementDefinition>
									<!-- FieldGroups -->
									<org.openmdx.ui1.ElementDefinition name="org:opencrx:kernel:account1:Account:Pane:Attr:Tab:91:Group:10">
										<_object>
											<active>true</active>
											<toolTip>
												<_item>字串</_item>
											</toolTip>
											<label>
												<_item>字串</_item>
											</label>
										</_object>
										<_content />
									</org.openmdx.ui1.ElementDefinition>
									<org.openmdx.ui1.ElementDefinition name="org:opencrx:kernel:account1:Account:Pane:Attr:Tab:91:Group:20">
										<_object>
											<active>true</active>
											<toolTip>
												<_item>數字</_item>
											</toolTip>
											<label>
												<_item>數字</_item>
											</label>
										</_object>
										<_content />
									</org.openmdx.ui1.ElementDefinition>
									<org.openmdx.ui1.ElementDefinition name="org:opencrx:kernel:account1:Account:Pane:Attr:Tab:91:Group:30">
										<_object>
											<active>true</active>
											<toolTip>
												<_item>布林值</_item>
											</toolTip>
											<label>
												<_item>不林值</_item>
											</label>
										</_object>
										<_content />
									</org.openmdx.ui1.ElementDefinition>
									<org.openmdx.ui1.ElementDefinition name="org:opencrx:kernel:account1:Account:Pane:Attr:Tab:91:Group:40">
										<_object>
											<active>true</active>
											<toolTip>
												<_item>代碼</_item>
											</toolTip>
											<label>
												<_item>代碼</_item>
											</label>
										</_object>
										<_content />
									</org.openmdx.ui1.ElementDefinition>
									<org.openmdx.ui1.ElementDefinition name="org:opencrx:kernel:account1:Account:Pane:Attr:Tab:91:Group:50">
										<_object>
											<active>true</active>
											<toolTip>
												<_item>日期時間</_item>
											</toolTip>
											<label>
												<_item>日期時間</_item>
											</label>
										</_object>
										<_content />
									</org.openmdx.ui1.ElementDefinition>
									<org.openmdx.ui1.ElementDefinition name="org:opencrx:kernel:account1:Account:Pane:Attr:Tab:91:Group:60">
										<_object>
											<active>true</active>
											<toolTip>
												<_item>日期</_item>
											</toolTip>
											<label>
												<_item>日期</_item>
											</label>
										</_object>
										<_content />
									</org.openmdx.ui1.ElementDefinition>
									<org.openmdx.ui1.ElementDefinition name="org:opencrx:kernel:account1:Account:Pane:Attr:Tab:91:Group:70">
										<_object>
											<active>true</active>
											<toolTip>
												<_item>搜尋欄位</_item>
											</toolTip>
											<label>
												<_item>搜訊欄位</_item>
											</label>
										</_object>
										<_content />
									</org.openmdx.ui1.ElementDefinition>
									<!--Element Definitions -->
									<org.openmdx.ui1.ElementDefinition name="org:opencrx:kernel:account1:Account:extString0">
										<_object>
											<active>true</active>
											<toolTip>
												<_item>擴展</_item>
											</toolTip>
											<label>
												<_item>擴展自傳0</_item>
											</label>
											<order>
												<_item>91</_item>
												<_item>10</_item>
												<_item>0</_item>
											</order>
										</_object>
										<_content />
									</org.openmdx.ui1.ElementDefinition>
									<org.openmdx.ui1.ElementDefinition name="org:opencrx:kernel:account1:Account:extString1">
										<_object>
											<active>true</active>
											<toolTip>
												<_item>擴展</_item>
											</toolTip>
											<label>
												<_item>擴展字串1</_item>
											</label>
											<order>
												<_item>91</_item>
												<_item>10</_item>
												<_item>10</_item>
											</order>
										</_object>
										<_content />
									</org.openmdx.ui1.ElementDefinition>
									<org.openmdx.ui1.ElementDefinition name="org:opencrx:kernel:account1:Account:extString2">
										<_object>
											<active>true</active>
											<toolTip>
												<_item>擴展</_item>
											</toolTip>
											<label>
												<_item>擴展字串2</_item>
											</label>
											<order>
												<_item>91</_item>
												<_item>10</_item>
												<_item>20</_item>
											</order>
										</_object>
										<_content />
									</org.openmdx.ui1.ElementDefinition>
									<org.openmdx.ui1.ElementDefinition name="org:opencrx:kernel:account1:Account:extString3">
										<_object>
											<active>true</active>
											<toolTip>
												<_item>擴展</_item>
											</toolTip>
											<label>
												<_item>擴展字串3</_item>
											</label>
											<order>
												<_item>91</_item>
												<_item>10</_item>
												<_item>30</_item>
											</order>
										</_object>
										<_content />
									</org.openmdx.ui1.ElementDefinition>
									<org.openmdx.ui1.ElementDefinition name="org:opencrx:kernel:account1:Account:extString4">
										<_object>
											<active>true</active>
											<toolTip>
												<_item>擴展</_item>
											</toolTip>
											<label>
												<_item>擴展字串4</_item>
											</label>
											<order>
												<_item>91</_item>
												<_item>10</_item>
												<_item>40</_item>
											</order>
										</_object>
										<_content />
									</org.openmdx.ui1.ElementDefinition>
									<org.openmdx.ui1.ElementDefinition name="org:opencrx:kernel:account1:Account:extString5">
										<_object>
											<active>true</active>
											<toolTip>
												<_item>擴展</_item>
											</toolTip>
											<label>
												<_item>擴展字串5</_item>
											</label>
											<order>
												<_item>91</_item>
												<_item>10</_item>
												<_item>50</_item>
											</order>
										</_object>
										<_content />
									</org.openmdx.ui1.ElementDefinition>
									<org.openmdx.ui1.ElementDefinition name="org:opencrx:kernel:account1:Account:extString6">
										<_object>
											<active>true</active>
											<toolTip>
												<_item>擴展</_item>
											</toolTip>
											<label>
												<_item>擴展字串6</_item>
											</label>
											<order>
												<_item>91</_item>
												<_item>10</_item>
												<_item>60</_item>
											</order>
										</_object>
										<_content />
									</org.openmdx.ui1.ElementDefinition>
									<org.openmdx.ui1.ElementDefinition name="org:opencrx:kernel:account1:Account:extString7">
										<_object>
											<active>true</active>
											<toolTip>
												<_item>擴展</_item>
											</toolTip>
											<label>
												<_item>擴展字串7</_item>
											</label>
											<order>
												<_item>91</_item>
												<_item>10</_item>
												<_item>70</_item>
											</order>
										</_object>
										<_content />
									</org.openmdx.ui1.ElementDefinition>
									<org.openmdx.ui1.ElementDefinition name="org:opencrx:kernel:account1:Account:extString8">
										<_object>
											<active>true</active>
											<toolTip>
												<_item>擴展</_item>
											</toolTip>
											<label>
												<_item>擴展字串8</_item>
											</label>
											<order>
												<_item>91</_item>
												<_item>10</_item>
												<_item>80</_item>
											</order>
										</_object>
										<_content />
									</org.openmdx.ui1.ElementDefinition>
									<org.openmdx.ui1.ElementDefinition name="org:opencrx:kernel:account1:Account:extString9">
										<_object>
											<active>true</active>
											<toolTip>
												<_item>擴展</_item>
											</toolTip>
											<label>
												<_item>擴展字串9</_item>
											</label>
											<order>
												<_item>91</_item>
												<_item>10</_item>
												<_item>90</_item>
											</order>
										</_object>
										<_content />
									</org.openmdx.ui1.ElementDefinition>
									<org.openmdx.ui1.ElementDefinition name="org:opencrx:kernel:account1:Account:extNumber0">
										<_object>
											<active>true</active>
											<toolTip>
												<_item>擴展</_item>
											</toolTip>
											<label>
												<_item>擴展數字0</_item>
											</label>
											<order>
												<_item>91</_item>
												<_item>20</_item>
												<_item>0</_item>
											</order>
										</_object>
										<_content />
									</org.openmdx.ui1.ElementDefinition>
									<org.openmdx.ui1.ElementDefinition name="org:opencrx:kernel:account1:Account:extNumber1">
										<_object>
											<active>true</active>
											<toolTip>
												<_item>擴展</_item>
											</toolTip>
											<label>
												<_item>擴展數字1</_item>
											</label>
											<order>
												<_item>91</_item>
												<_item>20</_item>
												<_item>10</_item>
											</order>
										</_object>
										<_content />
									</org.openmdx.ui1.ElementDefinition>
									<org.openmdx.ui1.ElementDefinition name="org:opencrx:kernel:account1:Account:extNumber2">
										<_object>
											<active>true</active>
											<toolTip>
												<_item>擴展</_item>
											</toolTip>
											<label>
												<_item>擴展數字2</_item>
											</label>
											<order>
												<_item>91</_item>
												<_item>20</_item>
												<_item>20</_item>
											</order>
										</_object>
										<_content />
									</org.openmdx.ui1.ElementDefinition>
									<org.openmdx.ui1.ElementDefinition name="org:opencrx:kernel:account1:Account:extNumber3">
										<_object>
											<active>true</active>
											<toolTip>
												<_item>擴展</_item>
											</toolTip>
											<label>
												<_item>擴展數字3</_item>
											</label>
											<order>
												<_item>91</_item>
												<_item>20</_item>
												<_item>30</_item>
											</order>
										</_object>
										<_content />
									</org.openmdx.ui1.ElementDefinition>
									<org.openmdx.ui1.ElementDefinition name="org:opencrx:kernel:account1:Account:extNumber4">
										<_object>
											<active>true</active>
											<toolTip>
												<_item>擴展</_item>
											</toolTip>
											<label>
												<_item>擴展數字4</_item>
											</label>
											<order>
												<_item>91</_item>
												<_item>20</_item>
												<_item>40</_item>
											</order>
										</_object>
										<_content />
									</org.openmdx.ui1.ElementDefinition>
									<org.openmdx.ui1.ElementDefinition name="org:opencrx:kernel:account1:Account:extNumber5">
										<_object>
											<active>true</active>
											<toolTip>
												<_item>擴展</_item>
											</toolTip>
											<label>
												<_item>擴展數字5</_item>
											</label>
											<order>
												<_item>91</_item>
												<_item>20</_item>
												<_item>50</_item>
											</order>
										</_object>
										<_content />
									</org.openmdx.ui1.ElementDefinition>
									<org.openmdx.ui1.ElementDefinition name="org:opencrx:kernel:account1:Account:extNumber6">
										<_object>
											<active>true</active>
											<toolTip>
												<_item>擴展</_item>
											</toolTip>
											<label>
												<_item>擴展數字6</_item>
											</label>
											<order>
												<_item>91</_item>
												<_item>20</_item>
												<_item>60</_item>
											</order>
										</_object>
										<_content />
									</org.openmdx.ui1.ElementDefinition>
									<org.openmdx.ui1.ElementDefinition name="org:opencrx:kernel:account1:Account:extNumber7">
										<_object>
											<active>true</active>
											<toolTip>
												<_item>擴展</_item>
											</toolTip>
											<label>
												<_item>擴展數字7</_item>
											</label>
											<order>
												<_item>91</_item>
												<_item>20</_item>
												<_item>70</_item>
											</order>
										</_object>
										<_content />
									</org.openmdx.ui1.ElementDefinition>
									<org.openmdx.ui1.ElementDefinition name="org:opencrx:kernel:account1:Account:extNumber8">
										<_object>
											<active>true</active>
											<toolTip>
												<_item>擴展</_item>
											</toolTip>
											<label>
												<_item>擴展數字8</_item>
											</label>
											<order>
												<_item>91</_item>
												<_item>20</_item>
												<_item>80</_item>
											</order>
										</_object>
										<_content />
									</org.openmdx.ui1.ElementDefinition>
									<org.openmdx.ui1.ElementDefinition name="org:opencrx:kernel:account1:Account:extNumber9">
										<_object>
											<active>true</active>
											<toolTip>
												<_item>擴展</_item>
											</toolTip>
											<label>
												<_item>擴展數字9</_item>
											</label>
											<order>
												<_item>91</_item>
												<_item>20</_item>
												<_item>90</_item>
											</order>
										</_object>
										<_content />
									</org.openmdx.ui1.ElementDefinition>
									<org.openmdx.ui1.ElementDefinition name="org:opencrx:kernel:account1:Account:extBoolean0">
										<_object>
											<active>true</active>
											<toolTip>
												<_item>擴展</_item>
											</toolTip>
											<label>
												<_item>擴展布林值0</_item>
											</label>
											<order>
												<_item>91</_item>
												<_item>30</_item>
												<_item>0</_item>
											</order>
										</_object>
										<_content />
									</org.openmdx.ui1.ElementDefinition>
									<org.openmdx.ui1.ElementDefinition name="org:opencrx:kernel:account1:Account:extBoolean1">
										<_object>
											<active>true</active>
											<toolTip>
												<_item>擴展</_item>
											</toolTip>
											<label>
												<_item>擴展布林值1</_item>
											</label>
											<order>
												<_item>91</_item>
												<_item>30</_item>
												<_item>10</_item>
											</order>
										</_object>
										<_content />
									</org.openmdx.ui1.ElementDefinition>
									<org.openmdx.ui1.ElementDefinition name="org:opencrx:kernel:account1:Account:extBoolean2">
										<_object>
											<active>true</active>
											<toolTip>
												<_item>擴展</_item>
											</toolTip>
											<label>
												<_item>擴展布林值2</_item>
											</label>
											<order>
												<_item>91</_item>
												<_item>30</_item>
												<_item>20</_item>
											</order>
										</_object>
										<_content />
									</org.openmdx.ui1.ElementDefinition>
									<org.openmdx.ui1.ElementDefinition name="org:opencrx:kernel:account1:Account:extBoolean3">
										<_object>
											<active>true</active>
											<toolTip>
												<_item>擴展</_item>
											</toolTip>
											<label>
												<_item>擴展布林值3</_item>
											</label>
											<order>
												<_item>91</_item>
												<_item>30</_item>
												<_item>30</_item>
											</order>
										</_object>
										<_content />
									</org.openmdx.ui1.ElementDefinition>
									<org.openmdx.ui1.ElementDefinition name="org:opencrx:kernel:account1:Account:extBoolean4">
										<_object>
											<active>true</active>
											<toolTip>
												<_item>擴展</_item>
											</toolTip>
											<label>
												<_item>擴展布林值4</_item>
											</label>
											<order>
												<_item>91</_item>
												<_item>30</_item>
												<_item>40</_item>
											</order>
										</_object>
										<_content />
									</org.openmdx.ui1.ElementDefinition>
									<org.openmdx.ui1.ElementDefinition name="org:opencrx:kernel:account1:Account:extBoolean5">
										<_object>
											<active>true</active>
											<toolTip>
												<_item>擴展</_item>
											</toolTip>
											<label>
												<_item>擴展布林值5</_item>
											</label>
											<order>
												<_item>91</_item>
												<_item>30</_item>
												<_item>50</_item>
											</order>
										</_object>
										<_content />
									</org.openmdx.ui1.ElementDefinition>
									<org.openmdx.ui1.ElementDefinition name="org:opencrx:kernel:account1:Account:extBoolean6">
										<_object>
											<active>true</active>
											<toolTip>
												<_item>擴展</_item>
											</toolTip>
											<label>
												<_item>擴展布林值6</_item>
											</label>
											<order>
												<_item>91</_item>
												<_item>30</_item>
												<_item>60</_item>
											</order>
										</_object>
										<_content />
									</org.openmdx.ui1.ElementDefinition>
									<org.openmdx.ui1.ElementDefinition name="org:opencrx:kernel:account1:Account:extBoolean7">
										<_object>
											<active>true</active>
											<toolTip>
												<_item>擴展</_item>
											</toolTip>
											<label>
												<_item>擴展布林值7</_item>
											</label>
											<order>
												<_item>91</_item>
												<_item>30</_item>
												<_item>70</_item>
											</order>
										</_object>
										<_content />
									</org.openmdx.ui1.ElementDefinition>
									<org.openmdx.ui1.ElementDefinition name="org:opencrx:kernel:account1:Account:extBoolean8">
										<_object>
											<active>true</active>
											<toolTip>
												<_item>擴展</_item>
											</toolTip>
											<label>
												<_item>擴展布林值8</_item>
											</label>
											<order>
												<_item>91</_item>
												<_item>30</_item>
												<_item>80</_item>
											</order>
										</_object>
										<_content />
									</org.openmdx.ui1.ElementDefinition>
									<org.openmdx.ui1.ElementDefinition name="org:opencrx:kernel:account1:Account:extBoolean9">
										<_object>
											<active>true</active>
											<toolTip>
												<_item>擴展</_item>
											</toolTip>
											<label>
												<_item>擴展布林值9</_item>
											</label>
											<order>
												<_item>91</_item>
												<_item>30</_item>
												<_item>90</_item>
											</order>
										</_object>
										<_content />
									</org.openmdx.ui1.ElementDefinition>
									<org.openmdx.ui1.ElementDefinition name="org:opencrx:kernel:account1:Account:extCode0">
										<_object>
											<active>true</active>
											<toolTip>
												<_item>擴展</_item>
											</toolTip>
											<label>
												<_item>擴展代碼0</_item>
											</label>
											<order>
												<_item>91</_item>
												<_item>40</_item>
												<_item>0</_item>
											</order>
										</_object>
										<_content />
									</org.openmdx.ui1.ElementDefinition>
									<org.openmdx.ui1.ElementDefinition name="org:opencrx:kernel:account1:Account:extCode1">
										<_object>
											<active>true</active>
											<toolTip>
												<_item>擴展</_item>
											</toolTip>
											<label>
												<_item>擴展代碼1</_item>
											</label>
											<order>
												<_item>91</_item>
												<_item>40</_item>
												<_item>10</_item>
											</order>
										</_object>
										<_content />
									</org.openmdx.ui1.ElementDefinition>
									<org.openmdx.ui1.ElementDefinition name="org:opencrx:kernel:account1:Account:extCode2">
										<_object>
											<active>true</active>
											<toolTip>
												<_item>擴展</_item>
											</toolTip>
											<label>
												<_item>擴展代碼2</_item>
											</label>
											<order>
												<_item>91</_item>
												<_item>40</_item>
												<_item>20</_item>
											</order>
										</_object>
										<_content />
									</org.openmdx.ui1.ElementDefinition>
									<org.openmdx.ui1.ElementDefinition name="org:opencrx:kernel:account1:Account:extCode3">
										<_object>
											<active>true</active>
											<toolTip>
												<_item>擴展</_item>
											</toolTip>
											<label>
												<_item>擴展代碼3</_item>
											</label>
											<order>
												<_item>91</_item>
												<_item>40</_item>
												<_item>30</_item>
											</order>
										</_object>
										<_content />
									</org.openmdx.ui1.ElementDefinition>
									<org.openmdx.ui1.ElementDefinition name="org:opencrx:kernel:account1:Account:extCode4">
										<_object>
											<active>true</active>
											<toolTip>
												<_item>擴展</_item>
											</toolTip>
											<label>
												<_item>擴展代碼4</_item>
											</label>
											<order>
												<_item>91</_item>
												<_item>40</_item>
												<_item>40</_item>
											</order>
										</_object>
										<_content />
									</org.openmdx.ui1.ElementDefinition>
									<org.openmdx.ui1.ElementDefinition name="org:opencrx:kernel:account1:Account:extCode5">
										<_object>
											<active>true</active>
											<toolTip>
												<_item>擴展</_item>
											</toolTip>
											<label>
												<_item>擴展代碼5</_item>
											</label>
											<order>
												<_item>91</_item>
												<_item>40</_item>
												<_item>50</_item>
											</order>
										</_object>
										<_content />
									</org.openmdx.ui1.ElementDefinition>
									<org.openmdx.ui1.ElementDefinition name="org:opencrx:kernel:account1:Account:extCode6">
										<_object>
											<active>true</active>
											<toolTip>
												<_item>擴展</_item>
											</toolTip>
											<label>
												<_item>擴展代碼6</_item>
											</label>
											<order>
												<_item>91</_item>
												<_item>40</_item>
												<_item>60</_item>
											</order>
										</_object>
										<_content />
									</org.openmdx.ui1.ElementDefinition>
									<org.openmdx.ui1.ElementDefinition name="org:opencrx:kernel:account1:Account:extCode7">
										<_object>
											<active>true</active>
											<toolTip>
												<_item>擴展</_item>
											</toolTip>
											<label>
												<_item>擴展代碼7</_item>
											</label>
											<order>
												<_item>91</_item>
												<_item>40</_item>
												<_item>70</_item>
											</order>
										</_object>
										<_content />
									</org.openmdx.ui1.ElementDefinition>
									<org.openmdx.ui1.ElementDefinition name="org:opencrx:kernel:account1:Account:extCode8">
										<_object>
											<active>true</active>
											<toolTip>
												<_item>擴展</_item>
											</toolTip>
											<label>
												<_item>擴展代碼8</_item>
											</label>
											<order>
												<_item>91</_item>
												<_item>40</_item>
												<_item>80</_item>
											</order>
										</_object>
										<_content />
									</org.openmdx.ui1.ElementDefinition>
									<org.openmdx.ui1.ElementDefinition name="org:opencrx:kernel:account1:Account:extCode9">
										<_object>
											<active>true</active>
											<toolTip>
												<_item>擴展</_item>
											</toolTip>
											<label>
												<_item>擴展代碼9</_item>
											</label>
											<order>
												<_item>91</_item>
												<_item>40</_item>
												<_item>90</_item>
											</order>
										</_object>
										<_content />
									</org.openmdx.ui1.ElementDefinition>
									<org.openmdx.ui1.ElementDefinition name="org:opencrx:kernel:account1:Account:extCode10">
										<_object>
											<active>true</active>
											<toolTip>
												<_item>擴展</_item>
											</toolTip>
											<label>
												<_item>擴展代碼10</_item>
											</label>
											<order>
												<_item>91</_item>
												<_item>40</_item>
												<_item>100</_item>
											</order>
										</_object>
										<_content />
									</org.openmdx.ui1.ElementDefinition>
									<org.openmdx.ui1.ElementDefinition name="org:opencrx:kernel:account1:Account:extCode11">
										<_object>
											<active>true</active>
											<toolTip>
												<_item>擴展</_item>
											</toolTip>
											<label>
												<_item>擴展代碼11</_item>
											</label>
											<order>
												<_item>91</_item>
												<_item>40</_item>
												<_item>110</_item>
											</order>
										</_object>
										<_content />
									</org.openmdx.ui1.ElementDefinition>
									<org.openmdx.ui1.ElementDefinition name="org:opencrx:kernel:account1:Account:extCode12">
										<_object>
											<active>true</active>
											<toolTip>
												<_item>擴展</_item>
											</toolTip>
											<label>
												<_item>擴展代碼12</_item>
											</label>
											<order>
												<_item>91</_item>
												<_item>40</_item>
												<_item>120</_item>
											</order>
										</_object>
										<_content />
									</org.openmdx.ui1.ElementDefinition>
									<org.openmdx.ui1.ElementDefinition name="org:opencrx:kernel:account1:Account:extCode13">
										<_object>
											<active>true</active>
											<toolTip>
												<_item>擴展</_item>
											</toolTip>
											<label>
												<_item>擴展代碼13</_item>
											</label>
											<order>
												<_item>91</_item>
												<_item>40</_item>
												<_item>130</_item>
											</order>
										</_object>
										<_content />
									</org.openmdx.ui1.ElementDefinition>
									<org.openmdx.ui1.ElementDefinition name="org:opencrx:kernel:account1:Account:extCode14">
										<_object>
											<active>true</active>
											<toolTip>
												<_item>擴展</_item>
											</toolTip>
											<label>
												<_item>擴展代碼14</_item>
											</label>
											<order>
												<_item>91</_item>
												<_item>40</_item>
												<_item>140</_item>
											</order>
										</_object>
										<_content />
									</org.openmdx.ui1.ElementDefinition>
									<org.openmdx.ui1.ElementDefinition name="org:opencrx:kernel:account1:Account:extCode15">
										<_object>
											<active>true</active>
											<toolTip>
												<_item>擴展</_item>
											</toolTip>
											<label>
												<_item>擴展代碼15</_item>
											</label>
											<order>
												<_item>91</_item>
												<_item>40</_item>
												<_item>150</_item>
											</order>
										</_object>
										<_content />
									</org.openmdx.ui1.ElementDefinition>
									<org.openmdx.ui1.ElementDefinition name="org:opencrx:kernel:account1:Account:extCode16">
										<_object>
											<active>true</active>
											<toolTip>
												<_item>擴展</_item>
											</toolTip>
											<label>
												<_item>擴展代碼16</_item>
											</label>
											<order>
												<_item>91</_item>
												<_item>40</_item>
												<_item>160</_item>
											</order>
										</_object>
										<_content />
									</org.openmdx.ui1.ElementDefinition>
									<org.openmdx.ui1.ElementDefinition name="org:opencrx:kernel:account1:Account:extCode17">
										<_object>
											<active>true</active>
											<toolTip>
												<_item>擴展</_item>
											</toolTip>
											<label>
												<_item>擴展代碼17</_item>
											</label>
											<order>
												<_item>91</_item>
												<_item>40</_item>
												<_item>170</_item>
											</order>
										</_object>
										<_content />
									</org.openmdx.ui1.ElementDefinition>
									<org.openmdx.ui1.ElementDefinition name="org:opencrx:kernel:account1:Account:extCode18">
										<_object>
											<active>true</active>
											<toolTip>
												<_item>擴展</_item>
											</toolTip>
											<label>
												<_item>擴展代碼18</_item>
											</label>
											<order>
												<_item>91</_item>
												<_item>40</_item>
												<_item>180</_item>
											</order>
										</_object>
										<_content />
									</org.openmdx.ui1.ElementDefinition>
									<org.openmdx.ui1.ElementDefinition name="org:opencrx:kernel:account1:Account:extCode19">
										<_object>
											<active>true</active>
											<toolTip>
												<_item>擴展</_item>
											</toolTip>
											<label>
												<_item>擴展代碼19</_item>
											</label>
											<order>
												<_item>91</_item>
												<_item>40</_item>
												<_item>190</_item>
											</order>
										</_object>
										<_content />
									</org.openmdx.ui1.ElementDefinition>
									<org.openmdx.ui1.ElementDefinition name="org:opencrx:kernel:account1:Account:extCode20">
										<_object>
											<active>true</active>
											<toolTip>
												<_item>擴展</_item>
											</toolTip>
											<label>
												<_item>擴展代碼20</_item>
											</label>
											<order>
												<_item>91</_item>
												<_item>40</_item>
												<_item>200</_item>
											</order>
										</_object>
										<_content />
									</org.openmdx.ui1.ElementDefinition>
									<org.openmdx.ui1.ElementDefinition name="org:opencrx:kernel:account1:Account:extCode21">
										<_object>
											<active>true</active>
											<toolTip>
												<_item>擴展</_item>
											</toolTip>
											<label>
												<_item>擴展代碼21</_item>
											</label>
											<order>
												<_item>91</_item>
												<_item>40</_item>
												<_item>210</_item>
											</order>
										</_object>
										<_content />
									</org.openmdx.ui1.ElementDefinition>
									<org.openmdx.ui1.ElementDefinition name="org:opencrx:kernel:account1:Account:extCode22">
										<_object>
											<active>true</active>
											<toolTip>
												<_item>擴展</_item>
											</toolTip>
											<label>
												<_item>擴展代碼22</_item>
											</label>
											<order>
												<_item>91</_item>
												<_item>40</_item>
												<_item>220</_item>
											</order>
										</_object>
										<_content />
									</org.openmdx.ui1.ElementDefinition>
									<org.openmdx.ui1.ElementDefinition name="org:opencrx:kernel:account1:Account:extCode23">
										<_object>
											<active>true</active>
											<toolTip>
												<_item>擴展</_item>
											</toolTip>
											<label>
												<_item>擴展代碼23</_item>
											</label>
											<order>
												<_item>91</_item>
												<_item>40</_item>
												<_item>230</_item>
											</order>
										</_object>
										<_content />
									</org.openmdx.ui1.ElementDefinition>
									<org.openmdx.ui1.ElementDefinition name="org:opencrx:kernel:account1:Account:extCode24">
										<_object>
											<active>true</active>
											<toolTip>
												<_item>擴展</_item>
											</toolTip>
											<label>
												<_item>擴展代碼24</_item>
											</label>
											<order>
												<_item>91</_item>
												<_item>40</_item>
												<_item>240</_item>
											</order>
										</_object>
										<_content />
									</org.openmdx.ui1.ElementDefinition>
									<org.openmdx.ui1.ElementDefinition name="org:opencrx:kernel:account1:Account:extCode25">
										<_object>
											<active>true</active>
											<toolTip>
												<_item>擴展</_item>
											</toolTip>
											<label>
												<_item>擴展代碼25</_item>
											</label>
											<order>
												<_item>91</_item>
												<_item>40</_item>
												<_item>250</_item>
											</order>
										</_object>
										<_content />
									</org.openmdx.ui1.ElementDefinition>
									<org.openmdx.ui1.ElementDefinition name="org:opencrx:kernel:account1:Account:extCode26">
										<_object>
											<active>true</active>
											<toolTip>
												<_item>擴展</_item>
											</toolTip>
											<label>
												<_item>擴展代碼26</_item>
											</label>
											<order>
												<_item>91</_item>
												<_item>40</_item>
												<_item>260</_item>
											</order>
										</_object>
										<_content />
									</org.openmdx.ui1.ElementDefinition>
									<org.openmdx.ui1.ElementDefinition name="org:opencrx:kernel:account1:Account:extCode27">
										<_object>
											<active>true</active>
											<toolTip>
												<_item>擴展</_item>
											</toolTip>
											<label>
												<_item>擴展代碼27</_item>
											</label>
											<order>
												<_item>91</_item>
												<_item>40</_item>
												<_item>270</_item>
											</order>
										</_object>
										<_content />
									</org.openmdx.ui1.ElementDefinition>
									<org.openmdx.ui1.ElementDefinition name="org:opencrx:kernel:account1:Account:extCode28">
										<_object>
											<active>true</active>
											<toolTip>
												<_item>擴展</_item>
											</toolTip>
											<label>
												<_item>擴展代碼28</_item>
											</label>
											<order>
												<_item>91</_item>
												<_item>40</_item>
												<_item>280</_item>
											</order>
										</_object>
										<_content />
									</org.openmdx.ui1.ElementDefinition>
									<org.openmdx.ui1.ElementDefinition name="org:opencrx:kernel:account1:Account:extCode29">
										<_object>
											<active>true</active>
											<toolTip>
												<_item>擴展</_item>
											</toolTip>
											<label>
												<_item>擴展代碼29</_item>
											</label>
											<order>
												<_item>91</_item>
												<_item>40</_item>
												<_item>290</_item>
											</order>
										</_object>
										<_content />
									</org.openmdx.ui1.ElementDefinition>
									<org.openmdx.ui1.ElementDefinition name="org:opencrx:kernel:account1:Account:extDateTime0">
										<_object>
											<active>true</active>
											<toolTip>
												<_item>擴展</_item>
											</toolTip>
											<label>
												<_item>擴展日期時間0</_item>
											</label>
											<order>
												<_item>91</_item>
												<_item>50</_item>
												<_item>0</_item>
											</order>
										</_object>
										<_content />
									</org.openmdx.ui1.ElementDefinition>
									<org.openmdx.ui1.ElementDefinition name="org:opencrx:kernel:account1:Account:extDateTime1">
										<_object>
											<active>true</active>
											<toolTip>
												<_item>擴展</_item>
											</toolTip>
											<label>
												<_item>擴展日期時間1</_item>
											</label>
											<order>
												<_item>91</_item>
												<_item>50</_item>
												<_item>10</_item>
											</order>
										</_object>
										<_content />
									</org.openmdx.ui1.ElementDefinition>
									<org.openmdx.ui1.ElementDefinition name="org:opencrx:kernel:account1:Account:extDateTime2">
										<_object>
											<active>true</active>
											<toolTip>
												<_item>擴展</_item>
											</toolTip>
											<label>
												<_item>擴展日期時間2</_item>
											</label>
											<order>
												<_item>91</_item>
												<_item>50</_item>
												<_item>20</_item>
											</order>
										</_object>
										<_content />
									</org.openmdx.ui1.ElementDefinition>
									<org.openmdx.ui1.ElementDefinition name="org:opencrx:kernel:account1:Account:extDateTime3">
										<_object>
											<active>true</active>
											<toolTip>
												<_item>擴展</_item>
											</toolTip>
											<label>
												<_item>擴展日期時間3</_item>
											</label>
											<order>
												<_item>91</_item>
												<_item>50</_item>
												<_item>30</_item>
											</order>
										</_object>
										<_content />
									</org.openmdx.ui1.ElementDefinition>
									<org.openmdx.ui1.ElementDefinition name="org:opencrx:kernel:account1:Account:extDateTime4">
										<_object>
											<active>true</active>
											<toolTip>
												<_item>擴展</_item>
											</toolTip>
											<label>
												<_item>擴展日期時間4</_item>
											</label>
											<order>
												<_item>91</_item>
												<_item>50</_item>
												<_item>40</_item>
											</order>
										</_object>
										<_content />
									</org.openmdx.ui1.ElementDefinition>
									<org.openmdx.ui1.ElementDefinition name="org:opencrx:kernel:account1:Account:extDateTime5">
										<_object>
											<active>true</active>
											<toolTip>
												<_item>擴展</_item>
											</toolTip>
											<label>
												<_item>擴展日期時間5</_item>
											</label>
											<order>
												<_item>91</_item>
												<_item>50</_item>
												<_item>50</_item>
											</order>
										</_object>
										<_content />
									</org.openmdx.ui1.ElementDefinition>
									<org.openmdx.ui1.ElementDefinition name="org:opencrx:kernel:account1:Account:extDateTime6">
										<_object>
											<active>true</active>
											<toolTip>
												<_item>擴展</_item>
											</toolTip>
											<label>
												<_item>擴展日期時間6</_item>
											</label>
											<order>
												<_item>91</_item>
												<_item>50</_item>
												<_item>60</_item>
											</order>
										</_object>
										<_content />
									</org.openmdx.ui1.ElementDefinition>
									<org.openmdx.ui1.ElementDefinition name="org:opencrx:kernel:account1:Account:extDateTime7">
										<_object>
											<active>true</active>
											<toolTip>
												<_item>擴展</_item>
											</toolTip>
											<label>
												<_item>擴展日期時間7</_item>
											</label>
											<order>
												<_item>91</_item>
												<_item>50</_item>
												<_item>70</_item>
											</order>
										</_object>
										<_content />
									</org.openmdx.ui1.ElementDefinition>
									<org.openmdx.ui1.ElementDefinition name="org:opencrx:kernel:account1:Account:extDateTime8">
										<_object>
											<active>true</active>
											<toolTip>
												<_item>擴展</_item>
											</toolTip>
											<label>
												<_item>擴展日期時間8</_item>
											</label>
											<order>
												<_item>91</_item>
												<_item>50</_item>
												<_item>80</_item>
											</order>
										</_object>
										<_content />
									</org.openmdx.ui1.ElementDefinition>
									<org.openmdx.ui1.ElementDefinition name="org:opencrx:kernel:account1:Account:extDateTime9">
										<_object>
											<active>true</active>
											<toolTip>
												<_item>擴展</_item>
											</toolTip>
											<label>
												<_item>擴展日期時間9</_item>
											</label>
											<order>
												<_item>91</_item>
												<_item>50</_item>
												<_item>90</_item>
											</order>
										</_object>
										<_content />
									</org.openmdx.ui1.ElementDefinition>
									<org.openmdx.ui1.ElementDefinition name="org:opencrx:kernel:account1:Account:extDate0">
										<_object>
											<active>true</active>
											<toolTip>
												<_item>擴展</_item>
											</toolTip>
											<label>
												<_item>擴展日期0</_item>
											</label>
											<order>
												<_item>91</_item>
												<_item>60</_item>
												<_item>0</_item>
											</order>
										</_object>
										<_content />
									</org.openmdx.ui1.ElementDefinition>
									<org.openmdx.ui1.ElementDefinition name="org:opencrx:kernel:account1:Account:extDate1">
										<_object>
											<active>true</active>
											<toolTip>
												<_item>擴展</_item>
											</toolTip>
											<label>
												<_item>擴展日期1</_item>
											</label>
											<order>
												<_item>91</_item>
												<_item>60</_item>
												<_item>10</_item>
											</order>
										</_object>
										<_content />
									</org.openmdx.ui1.ElementDefinition>
									<org.openmdx.ui1.ElementDefinition name="org:opencrx:kernel:account1:Account:extDate2">
										<_object>
											<active>true</active>
											<toolTip>
												<_item>擴展</_item>
											</toolTip>
											<label>
												<_item>擴展日期2</_item>
											</label>
											<order>
												<_item>91</_item>
												<_item>60</_item>
												<_item>20</_item>
											</order>
										</_object>
										<_content />
									</org.openmdx.ui1.ElementDefinition>
									<org.openmdx.ui1.ElementDefinition name="org:opencrx:kernel:account1:Account:extDate3">
										<_object>
											<active>true</active>
											<toolTip>
												<_item>擴展</_item>
											</toolTip>
											<label>
												<_item>擴展日期3</_item>
											</label>
											<order>
												<_item>91</_item>
												<_item>60</_item>
												<_item>30</_item>
											</order>
										</_object>
										<_content />
									</org.openmdx.ui1.ElementDefinition>
									<org.openmdx.ui1.ElementDefinition name="org:opencrx:kernel:account1:Account:extDate4">
										<_object>
											<active>true</active>
											<toolTip>
												<_item>擴展</_item>
											</toolTip>
											<label>
												<_item>擴展日期4</_item>
											</label>
											<order>
												<_item>91</_item>
												<_item>60</_item>
												<_item>40</_item>
											</order>
										</_object>
										<_content />
									</org.openmdx.ui1.ElementDefinition>
									<org.openmdx.ui1.ElementDefinition name="org:opencrx:kernel:account1:Account:extDate5">
										<_object>
											<active>true</active>
											<toolTip>
												<_item>擴展</_item>
											</toolTip>
											<label>
												<_item>擴展日期5</_item>
											</label>
											<order>
												<_item>91</_item>
												<_item>60</_item>
												<_item>50</_item>
											</order>
										</_object>
										<_content />
									</org.openmdx.ui1.ElementDefinition>
									<org.openmdx.ui1.ElementDefinition name="org:opencrx:kernel:account1:Account:extDate6">
										<_object>
											<active>true</active>
											<toolTip>
												<_item>擴展</_item>
											</toolTip>
											<label>
												<_item>擴展日期6</_item>
											</label>
											<order>
												<_item>91</_item>
												<_item>60</_item>
												<_item>60</_item>
											</order>
										</_object>
										<_content />
									</org.openmdx.ui1.ElementDefinition>
									<org.openmdx.ui1.ElementDefinition name="org:opencrx:kernel:account1:Account:extDate7">
										<_object>
											<active>true</active>
											<toolTip>
												<_item>擴展</_item>
											</toolTip>
											<label>
												<_item>擴展日期7</_item>
											</label>
											<order>
												<_item>91</_item>
												<_item>60</_item>
												<_item>70</_item>
											</order>
										</_object>
										<_content />
									</org.openmdx.ui1.ElementDefinition>
									<org.openmdx.ui1.ElementDefinition name="org:opencrx:kernel:account1:Account:extDate8">
										<_object>
											<active>true</active>
											<toolTip>
												<_item>擴展</_item>
											</toolTip>
											<label>
												<_item>擴展日期8</_item>
											</label>
											<order>
												<_item>91</_item>
												<_item>60</_item>
												<_item>80</_item>
											</order>
										</_object>
										<_content />
									</org.openmdx.ui1.ElementDefinition>
									<org.openmdx.ui1.ElementDefinition name="org:opencrx:kernel:account1:Account:extDate9">
										<_object>
											<active>true</active>
											<toolTip>
												<_item>擴展</_item>
											</toolTip>
											<label>
												<_item>擴展日期9</_item>
											</label>
											<order>
												<_item>91</_item>
												<_item>60</_item>
												<_item>90</_item>
											</order>
										</_object>
										<_content />
									</org.openmdx.ui1.ElementDefinition>
									<org.openmdx.ui1.ElementDefinition name="org:opencrx:kernel:account1:Account:searchName">
										<_object>
											<active>true</active>
											<toolTip>
												<_item>擴展</_item>
											</toolTip>
											<label>
												<_item>搜尋名稱</_item>
											</label>
											<order>
												<_item>91</_item>
												<_item>70</_item>
												<_item>0</_item>
											</order>
										</_object>
										<_content />
									</org.openmdx.ui1.ElementDefinition>
									<org.openmdx.ui1.ElementDefinition name="org:opencrx:kernel:account1:Account:searchPostal1AddressLine">
										<_object>
											<active>true</active>
											<toolTip>
												<_item>擴展</_item>
											</toolTip>
											<label>
												<_item>搜索郵政1地址行</_item>
											</label>
											<order>
												<_item>91</_item>
												<_item>70</_item>
												<_item>5</_item>
											</order>
										</_object>
										<_content />
									</org.openmdx.ui1.ElementDefinition>
									<org.openmdx.ui1.ElementDefinition name="org:opencrx:kernel:account1:Account:searchPostal1Street">
										<_object>
											<active>true</active>
											<toolTip>
												<_item>擴展</_item>
											</toolTip>
											<label>
												<_item>搜索郵政1路</_item>
											</label>
											<order>
												<_item>91</_item>
												<_item>70</_item>
												<_item>10</_item>
											</order>
										</_object>
										<_content />
									</org.openmdx.ui1.ElementDefinition>
									<org.openmdx.ui1.ElementDefinition name="org:opencrx:kernel:account1:Account:searchPostal1StreetNumber">
										<_object>
											<active>true</active>
											<toolTip>
												<_item>擴展</_item>
											</toolTip>
											<label>
												<_item>搜索郵政1路號</_item>
											</label>
											<order>
												<_item>91</_item>
												<_item>70</_item>
												<_item>20</_item>
											</order>
										</_object>
										<_content />
									</org.openmdx.ui1.ElementDefinition>
									<org.openmdx.ui1.ElementDefinition name="org:opencrx:kernel:account1:Account:searchPostal1PostalCode">
										<_object>
											<active>true</active>
											<toolTip>
												<_item>擴展</_item>
											</toolTip>
											<label>
												<_item>搜索郵政1郵政代碼</_item>
											</label>
											<order>
												<_item>91</_item>
												<_item>70</_item>
												<_item>30</_item>
											</order>
										</_object>
										<_content />
									</org.openmdx.ui1.ElementDefinition>
									<org.openmdx.ui1.ElementDefinition name="org:opencrx:kernel:account1:Account:searchPostal1City">
										<_object>
											<active>true</active>
											<toolTip>
												<_item>擴展</_item>
											</toolTip>
											<label>
												<_item>搜尋郵政1城市</_item>
											</label>
											<order>
												<_item>91</_item>
												<_item>70</_item>
												<_item>40</_item>
											</order>
										</_object>
										<_content />
									</org.openmdx.ui1.ElementDefinition>
									<org.openmdx.ui1.ElementDefinition name="org:opencrx:kernel:account1:Account:searchPostal1Country">
										<_object>
											<active>true</active>
											<toolTip>
												<_item>擴展</_item>
											</toolTip>
											<label>
												<_item>搜尋郵政1國家</_item>
											</label>
											<order>
												<_item>91</_item>
												<_item>70</_item>
												<_item>50</_item>
											</order>
										</_object>
										<_content />
									</org.openmdx.ui1.ElementDefinition>
									<org.openmdx.ui1.ElementDefinition name="org:opencrx:kernel:account1:Account:searchPostal1State">
										<_object>
											<active>true</active>
											<toolTip>
												<_item>擴展</_item>
											</toolTip>
											<label>
												<_item>搜尋郵政1州</_item>
											</label>
											<order>
												<_item>91</_item>
												<_item>70</_item>
												<_item>60</_item>
											</order>
										</_object>
										<_content />
									</org.openmdx.ui1.ElementDefinition>
									<org.openmdx.ui1.ElementDefinition name="org:opencrx:kernel:account1:Account:searchPostal2AddressLine">
										<_object>
											<active>true</active>
											<toolTip>
												<_item>擴展</_item>
											</toolTip>
											<label>
												<_item>搜索郵政2地址行</_item>
											</label>
											<order>
												<_item>91</_item>
												<_item>70</_item>
												<_item>70</_item>
											</order>
										</_object>
										<_content />
									</org.openmdx.ui1.ElementDefinition>
									<org.openmdx.ui1.ElementDefinition name="org:opencrx:kernel:account1:Account:searchPostal2Street">
										<_object>
											<active>true</active>
											<toolTip>
												<_item>擴展</_item>
											</toolTip>
											<label>
												<_item>搜索郵政2路</_item>
											</label>
											<order>
												<_item>91</_item>
												<_item>70</_item>
												<_item>80</_item>
											</order>
										</_object>
										<_content />
									</org.openmdx.ui1.ElementDefinition>
									<org.openmdx.ui1.ElementDefinition name="org:opencrx:kernel:account1:Account:searchPostal2StreetNumber">
										<_object>
											<active>true</active>
											<toolTip>
												<_item>擴展</_item>
											</toolTip>
											<label>
												<_item>搜索郵政2路號</_item>
											</label>
											<order>
												<_item>91</_item>
												<_item>70</_item>
												<_item>90</_item>
											</order>
										</_object>
										<_content />
									</org.openmdx.ui1.ElementDefinition>
									<org.openmdx.ui1.ElementDefinition name="org:opencrx:kernel:account1:Account:searchPostal2PostalCode">
										<_object>
											<active>true</active>
											<toolTip>
												<_item>擴展</_item>
											</toolTip>
											<label>
												<_item>搜索郵政2郵政代碼</_item>
											</label>
											<order>
												<_item>91</_item>
												<_item>70</_item>
												<_item>100</_item>
											</order>
										</_object>
										<_content />
									</org.openmdx.ui1.ElementDefinition>
									<org.openmdx.ui1.ElementDefinition name="org:opencrx:kernel:account1:Account:searchPostal2City">
										<_object>
											<active>true</active>
											<toolTip>
												<_item>擴展</_item>
											</toolTip>
											<label>
												<_item>搜索郵政2城市</_item>
											</label>
											<order>
												<_item>91</_item>
												<_item>70</_item>
												<_item>110</_item>
											</order>
										</_object>
										<_content />
									</org.openmdx.ui1.ElementDefinition>
									<org.openmdx.ui1.ElementDefinition name="org:opencrx:kernel:account1:Account:searchPostal2Country">
										<_object>
											<active>true</active>
											<toolTip>
												<_item>擴展</_item>
											</toolTip>
											<label>
												<_item>搜索郵政2國家</_item>
											</label>
											<order>
												<_item>91</_item>
												<_item>70</_item>
												<_item>120</_item>
											</order>
										</_object>
										<_content />
									</org.openmdx.ui1.ElementDefinition>
									<org.openmdx.ui1.ElementDefinition name="org:opencrx:kernel:account1:Account:searchPostal2State">
										<_object>
											<active>true</active>
											<toolTip>
												<_item>擴展</_item>
											</toolTip>
											<label>
												<_item>搜索郵政2州</_item>
											</label>
											<order>
												<_item>91</_item>
												<_item>70</_item>
												<_item>130</_item>
											</order>
										</_object>
										<_content />
									</org.openmdx.ui1.ElementDefinition>
									<org.openmdx.ui1.ElementDefinition name="org:opencrx:kernel:account1:Account:searchEmail1">
										<_object>
											<active>true</active>
											<toolTip>
												<_item>擴展</_item>
											</toolTip>
											<label>
												<_item>搜尋電子郵件1</_item>
											</label>
											<order>
												<_item>91</_item>
												<_item>70</_item>
												<_item>140</_item>
											</order>
										</_object>
										<_content />
									</org.openmdx.ui1.ElementDefinition>
									<org.openmdx.ui1.ElementDefinition name="org:opencrx:kernel:account1:Account:searchEmail2">
										<_object>
											<active>true</active>
											<toolTip>
												<_item>擴展</_item>
											</toolTip>
											<label>
												<_item>搜尋電子郵件2</_item>
											</label>
											<order>
												<_item>91</_item>
												<_item>70</_item>
												<_item>150</_item>
											</order>
										</_object>
										<_content />
									</org.openmdx.ui1.ElementDefinition>
									<org.openmdx.ui1.ElementDefinition name="org:opencrx:kernel:account1:Account:searchPhone1">
										<_object>
											<active>true</active>
											<toolTip>
												<_item>擴展</_item>
											</toolTip>
											<label>
												<_item>搜尋電話1</_item>
											</label>
											<order>
												<_item>91</_item>
												<_item>70</_item>
												<_item>160</_item>
											</order>
										</_object>
										<_content />
									</org.openmdx.ui1.ElementDefinition>
									<org.openmdx.ui1.ElementDefinition name="org:opencrx:kernel:account1:Account:searchPhone2">
										<_object>
											<active>true</active>
											<toolTip>
												<_item>擴展</_item>
											</toolTip>
											<label>
												<_item>搜尋電話2</_item>
											</label>
											<order>
												<_item>91</_item>
												<_item>70</_item>
												<_item>170</_item>
											</order>
										</_object>
										<_content />
									</org.openmdx.ui1.ElementDefinition>
									<org.openmdx.ui1.ElementDefinition name="org:opencrx:kernel:account1:Account:searchMobile1">
										<_object>
											<active>true</active>
											<toolTip>
												<_item>擴展</_item>
											</toolTip>
											<label>
												<_item>搜尋行動電話1</_item>
											</label>
											<order>
												<_item>91</_item>
												<_item>70</_item>
												<_item>180</_item>
											</order>
										</_object>
										<_content />
									</org.openmdx.ui1.ElementDefinition>
									<org.openmdx.ui1.ElementDefinition name="org:opencrx:kernel:account1:Account:searchMobile2">
										<_object>
											<active>true</active>
											<toolTip>
												<_item>擴展</_item>
											</toolTip>
											<label>
												<_item>搜尋行動電話2</_item>
											</label>
											<order>
												<_item>91</_item>
												<_item>70</_item>
												<_item>190</_item>
											</order>
										</_object>
										<_content />
									</org.openmdx.ui1.ElementDefinition>

								</elementDefinition>
							</_content>
						</org.openmdx.ui1.Segment>
					</segment>
				</_content>
			</org.openmdx.base.Provider>
		</provider>
	</_content>
</org.openmdx.base.Authority>
